{
    "제목": [
        "중화인민공화국중화인민공화국중화인민공화국중화인민공화국중화인민공화국"
    ],
    "상태": [
        "소련 사회주의 공화국 (1922-1991)"
    ],
    "수도": [
        "미스키"
    ],
    "공통 언어": [
        "공식 언어 :, 벨라루스어 · 러시아어, 소수 언어 :, 폴란드어 · 우크라이나어 · Yiddish"
    ],
    "정부": [
        "유니터 마르크스-레닌주의 단일당 소련식 사회주의 공화국 (1920-1929; 1953-1990), 스탈린주의 단일당 독재 정권 (1929-1953), 유니터 의회 공화국 (1990-1991)"
    ],
    "첫 번째 장관": [
        "Vilhelm Knorinsh (첫 번째) (1920-1923)",
        "Vyacheslav Kebich (최종) (1990-1991)"
    ],
    "국가장": [
        "알렉산더 체르비코프 (첫 번째) (1920-1937)"
    ],
    "국장": [
        "Stanislav Shushkevich (마지막) (1991)"
    ],
    "정부 장관": [
        "알렉산더 체르비아코프 (첫 번째) (1920-1924)"
    ],
    "의회": [
        "최고의 소련"
    ],
    "역사 시대": [
        "20세기"
    ],
    "공화국 선언": [
        "1 월 1919"
    ],
    "소련 공화국 선언": [
        "1920년 7월 31일"
    ],
    "소련에 입국": [
        "1922년 12월 30일"
    ],
    "서베르셀로나의 합병": [
        "1939년 11월 15일"
    ],
    "유엔 멤버십": [
        "1945년 10월 24일"
    ],
    "주권 선언": [
        "1990년 7월 27일"
    ],
    "독립 선언": [
        "1991년 8월 25일"
    ],
    "벨라루스 공화국": [
        "1991년 9월 9일"
    ],
    "국제적으로 인정된": [
        "1991년 12월 26일"
    ],
    "새로운 헌법": [
        "1994년 3월 15일"
    ]
}