{
    "제목": [
        "Julian Lennon"
    ],
    "출생 이름": [
        "John Charles Julian Lennon"
    ],
    "또한 알려진": [
        "Jules"
    ],
    "탄생": [
        "( 1963-04-08 ) 1963년 4월 8일 (55세) 리버풀, 영국"
    ],
    "장르": [
        "Pop rock"
    ],
    "직업": [
        "노래 작가",
        "예술가",
        "사진 작가"
    ],
    "도구들": [
        "‘소리’"
    ],
    "뮤지션": [
        "기타"
    ],
    "도구": [
        "키보드"
    ],
    "활동년": [
        "1974년 현재"
    ],
    "라벨": [
        "Atlantic"
    ],
    "Labels": [
        "Music from Another Room",
        "아티스트"
    ],
    "태그": [
        "카리스마"
    ],
    "웹사이트": [
        "julianlennon.com"
    ]
}