{
    "제목": [
        "Justin Theroux"
    ],
    "태어난": [
        "1971년 8월 10일 (47세) 워싱턴 D.C., 미국"
    ],
    "출생 이름": [
        "Justin Paul Theroux"
    ],
    "알마 매터": [
        "벤닝턴 대학"
    ],
    "직업": [
        "배우",
        "코미디언",
        "제조사",
        "작가"
    ],
    "활동 년": [
        "1995-현재"
    ],
    "배우자": [
        "제니퍼 애니스턴 ( m. 2015; 9 월 2018)"
    ],
    "파트너": [
        "히디 비벤스 (1997-2011)"
    ],
    "친척": [
        "Alexander Theroux (아버지의 삼촌)",
        "Paul Theroux (아버지의 삼촌)",
        "Peter Theroux (아버지의 삼촌)",
        "Marcel Theroux (아버지의 첫 사촌)",
        "Louis Theroux (아버지의 첫 사촌)"
    ]
}