{
    "타이틀": [
        "콜로스"
    ],
    "감독": [
        "Nacho Vigalondo"
    ],
    "제작자": [
        "Nahikari Ipina",
        "Russell Levine",
        "Nicolas Chartier",
        "Zev Foreman",
        "Dominic Rustam"
    ],
    "작가": [
        "Nacho Vigalondo"
    ],
    "주연": [
        "Anne Hathaway",
        "Jason Sudeikis",
        "Dan Stevens",
        "오스틴 스토웰",
        "티ム 블레이크 넬슨"
    ],
    "음악": [
        "Bear McCreary"
    ],
    "영화": [
        "Eric Kress"
    ],
    "에 의해 편집": [
        "Ben Baudhuin"
    ],
    "편집자": [
        "Luke Doolan"
    ],
    "제작 회사": [
        "Voltage Pictures",
        "Route One Entertainment",
        "Legion M",
        "Sayaka Producciones",
        "Brightlight Pictures"
    ],
    "생산 회사": [
        "연합 투자 파트너"
    ],
    "에 의해 배포": [
        "Neon"
    ],
    "릴리스 날짜": [
        "2016년 9월 9일 (2016-09-09) (TIFF)",
        "2017년 4월 7일 (2017-04-07) (미국)"
    ],
    "실행 시간": [
        "110 분"
    ],
    "국가": [
        "캐나다",
        "스페인"
    ],
    "언어": [
        "영어"
    ],
    "예산": [
        "$15 백만"
    ],
    "박스 오피스": [
        "$4.5 백만"
    ]
}