{
    "\u6807\u9898": [
        "\u201c\u963f\u65af\u7279\u4e39\u201d"
    ],
    "\u53d1\u97f3": [
        "/\u02c8\u00e6st\u0259ti\u02d0n, -t\u026an/ ( AS-t\u0259-teen, -\u2060tin )"
    ],
    "\u5916\u89c2": [
        "\u672a\u77e5,\u53ef\u80fd\u662f\u91d1\u5c5e"
    ],
    "\u8d28\u91cf\u53f7": [
        "210(\u6700\u7a33\u5b9a\u7684\u540c\u4f4d\u7d20)"
    ],
    "\u539f\u5b50\u6570(Z)": [
        "85"
    ],
    "\u7ec4": [
        "\u7ec4 17 (\u7d20)"
    ],
    "\u671f": [
        "\u671f 6"
    ],
    "\u533a\u5757": [
        "p \u533a\u5757"
    ],
    "\u5143\u7d20\u7c7b\u522b": [
        "\u91d1\u5c5e,\u6709\u65f6\u88ab\u5f52\u7c7b\u4e3a\u975e\u91d1\u5c5e\u6216\u91d1\u5c5e"
    ],
    "\u7535\u5b50\u914d\u7f6e": [
        "[Xe] 4f 14 5d 10 6s 2 6p 5"
    ],
    "\u6bcf\u4e2a\u58f3\u7684\u7535\u5b50": [
        "2, 8, 18, 32, 18, 7"
    ],
    "\u9636\u6bb5\u5728 STP": [
        "\u56fa\u4f53"
    ],
    "\u6cb8\u70b9": [
        "( 2 ) 503 \u00b1 3 K (230 \u00b1 3 \u00b0C, 445 \u00b1 5 \u00b0F) (\u4f30\u8ba1)"
    ],
    "\u5bc6\u5ea6(\u8fd1 r.t.)": [
        "(\u5728 2 ) 6.35\u00b10.15 g/cm 3 (\u9884\u6d4b)"
    ],
    "\u5206\u5b50\u4f53\u79ef": [
        "( 2 ) 32.94 cm 3 /mol (\u9884\u6d4b)"
    ],
    "\u84b8\u53d1\u6e29\u5ea6": [
        "(At 2 ) 54.39 kJ/mol"
    ],
    "\u6c27\u5316\u72b6\u6001": [
        "\u22121, +1, +3, +5, +7"
    ],
    "\u7535\u5b50\u5426\u5b9a\u6027": [
        "\u5e73\u8861\u5c3a\u5ea6: 2.2"
    ],
    "\u79bb\u5b50\u80fd\u91cf": [
        "1 \u4e2a: 899.003 kJ/mol"
    ],
    "Covalent \u534a\u5f84": [
        "150 pm"
    ],
    "\u8303\u5fb7\u74e6\u5c14\u65af\u534a\u5f84": [
        "20 \u70b9"
    ],
    "\u81ea\u7136\u53d1\u751f": [
        "\u4ece\u8870\u53d8"
    ],
    "\u70ed\u5bfc\u7387": [
        "1.7 W/(m\u00b7K)"
    ],
    "CAS \u53f7\u7801": [
        "7440-68-8"
    ],
    "\u540d\u79f0": [
        "\u6765\u81ea\u5e0c\u814a\u8bed astatos (\u03b1\u03c3\u03c4\u03b1\u03c4\u03bf\u03c2),\u610f\u601d\u662f\u201c\u4e0d\u7a33\u5b9a\u201d"
    ],
    "\u53d1\u73b0": [
        "\u6234\u5c14\u00b7R\u00b7\u79d1\u68ee,\u80af\u5c3c\u601d\u00b7\u7f57\u65af\u00b7\u9ea6\u80af\u9f50,\u827e\u7c73\u5229\u5965\u00b7\u585e\u683c\u96f7(1940)"
    ]
}