{
    "\u6807\u9898": [
        "\u5730\u72f1\u4e4b\u6218"
    ],
    "\u827a\u672f\u5bb6": [
        "\u201cMet Meat Loaf\u201d"
    ],
    "\u53d1\u5e03": [
        "1977\u5e7410\u670821\u65e5"
    ],
    "\u5f55\u5236": [
        "1975-1976"
    ],
    "\u5de5\u4f5c\u5ba4": [
        "8 \u8d1d\u5c14\u65af\u7ef4\u5c14\u5de5\u4f5c\u5ba4,\u4f0d\u5fb7\u65af\u6258\u514b,\u7ebd\u7ea6",
        "Utopia Sound, \u6e56\u5c71, \u7ebd\u7ea6",
        "The Hit Factory,\u7ebd\u7ea6,\u7ebd\u7ea6",
        "\u97f3\u4e50\u4e4b\u5bb6, \u897f\u6a59, NJ"
    ],
    "\u7c7b\u578b": [
        "\u6447\u6eda",
        "\u683c\u62c9\u59c6\u6447\u6eda",
        "\u91cd\u91d1\u5c5e"
    ],
    "\u957f\u5ea6": [
        "46:33"
    ],
    "\u6807\u7b7e": [
        "\u201cCleveland International / Epic\u201d"
    ],
    "\u5236\u7247\u4eba": [
        "\u201cTodd Rundgren\u201d"
    ],
    "\u65f6\u95f4\u8868": [
        "\u300aStoney & Meatloaf\u300b(1971)",
        "\u6253\u51fa\u5730\u72f1(Bat Out of Hell, 1977)",
        "\u300a\u6b7b\u7684\u547c\u5524\u8005\u300b(Dead Ringer, 1981)"
    ],
    "\u5355\u66f2": [
        "You Took the Words Right Out of My Mouth (\u70ed\u590f\u591c) \u53d1\u884c:1977\u5e7410\u6708",
        "Two Out of Three Ain't Bad 1978\u5e742\u6708\u53d1\u884c",
        "Paradise by the Dashboard Light \u53d1\u884c:1978\u5e748\u6708"
    ]
}