{
    "\u6807\u9898": [
        "\u201cCarrie\u201d"
    ],
    "\u5bfc\u6f14": [
        "\u201cKimberly Peirce\u201d"
    ],
    "\u5236\u7247\u4eba": [
        "\u201cKevin Misher\u201d"
    ],
    "\u5267\u672c": [
        "\u201c\u52b3\u4f26\u65af\u00b7D\u00b7\u79d1\u6069,\u7f57\u4f2f\u6258\u00b7\u963f\u5409\u5c14\u00b7\u8428\u5361\u8428\u201d"
    ],
    "\u57fa\u4e8e": [
        "\u5361\u91cc, \u7531\u65af\u8482\u82ac\u00b7\u91d1\u5361\u91cc(1976\u5e74\u7535\u5f71)"
    ],
    "\u4e3b\u6f14": [
        "\u514b\u6d1b\u00b7\u683c\u96f7\u65af\u00b7\u83ab\u96f7\u8328",
        "\u6731\u8fea\u00b7\u683c\u91cc\u5c14",
        "Portia Doubleday",
        "\u4e9a\u5386\u514b\u65af\u00b7\u62c9\u585e\u5c14",
        "\u52a0\u5e03\u91cc\u57c3\u62c9\u00b7\u5a01\u5c14\u5fb7",
        "\u6731\u5229\u5b89\u00b7\u6469\u5c14"
    ],
    "\u97f3\u4e50": [
        "\u201c\u9a6c\u53ef\u00b7\u8d1d\u5c14\u7279\u62c9\u7c73\u201d"
    ],
    "\u7535\u5f71": [
        "\u201c\u53f2\u8482\u592b\u00b7\u8036\u5fb7\u6797\u201d"
    ],
    "\u7f16\u8f91": [
        "\u201cLee Percy\u201d"
    ],
    "\u5236\u4f5c\u516c\u53f8": [
        "\u201cMetro-Goldwyn-Mayer Pictures\u201d",
        "\u201c\u5c4f\u5e55\u5b9d\u77f3\u201d",
        "\u201cMisher Films\u201d"
    ],
    "\u53d1\u884c": [
        "\u7d22\u5c3c\u5f71\u50cf\u53d1\u5e03"
    ],
    "\u767c\u884c\u65e5\u671f": [
        "2013\u5e7410\u67087\u65e5 (2013-10-07) (Arclight Hollywood)"
    ],
    "\u53d1\u5e03\u65e5\u671f": [
        "2013\u5e7410\u670818\u65e5 (2013-10-18) (\u7f8e\u56fd)"
    ],
    "\u8fd0\u884c\u65f6\u95f4": [
        "99 \u5206\u949f"
    ],
    "\u56fd\u5bb6": [
        "\u201c\u7f8e\u56fd\u201d"
    ],
    "\u8bed\u8a00": [
        "\u201c\u82f1\u8bed\u201d"
    ],
    "\u9884\u7b97": [
        "30 \u4e07\u7f8e\u5143"
    ],
    "Box office": [
        "85 \u4e07\u7f8e\u5143"
    ]
}