{
    "\u6807\u9898": [
        "\u201c\u7f8e\u98df\u4e0e\u996e\u6599\u201d"
    ],
    "\u7c7b\u578b": [
        "\u201c\u9152\u7cbe\u201d"
    ],
    "\u5236\u9020\u5546": [
        "\u201cG\u2019Day Imports\u201d"
    ],
    "\u539f\u4ea7\u5730": [
        "\u201c\u6fb3\u5927\u5229\u4e9a\u201d"
    ],
    "\u4ecb\u7ecd": [
        "2006\u5e74\u5728\u7f8e\u56fd"
    ],
    "\u9152\u7cbe\u91cf": [
        "40.0%"
    ],
    "\u8bc1\u636e(\u7f8e\u56fd)": [
        "80"
    ],
    "\u76f8\u5173\u4ea7\u54c1": [
        "\u9152\u7cbe\u6e05\u5355"
    ]
}