{
    "Titel": [
        "Converge"
    ],
    "Herkunft": [
        "Salem, Massachusetts, USA."
    ],
    "Genres": [
        "Metalcore",
        "Hardcore Punk",
        "Mathcore",
        "post-hardcore"
    ],
    "Jahre aktiv": [
        "1990 - präsent"
    ],
    "Labels": [
        "Gleiches",
        "Deathwish",
        "Epitaph"
    ],
    "Associated Acts": [
        "Supermachiner",
        "Cave In",
        "Kid Kilowatt",
        "Mutoid Man",
        "Chelsea Wolfe"
    ],
    "Assoziierte Acts": [
        "Bane",
        "Blaues/Grünes Herz",
        "Steve Von Till"
    ],
    "Webseite": [
        "convergencecult.com"
    ]
}