{
    "Titel": [
        "Jim Mattis"
    ],
    "Nickname(n)": [
        "„Chaos (Rufzeichen)",
        "„ Krieger-Monk",
        "Mädchen"
    ],
    "Jahre des Dienstes": [
        "1969-2013"
    ],
    "Kommandos": [
        "„U.S. Central Command",
        " U.S. Joint Forces Command ",
        "„I marine Expeditionstruppe",
        " U.S. Marine Forces Central Command ",
        "„ Marine Corps Combat Development Command",
        " 1. Marine-Division ",
        " 1. Marine-Expeditionsbrigade ",
        "7. Marines"
    ],
    "Befehle": [
        "„ Transformation des Oberbefehlshabers der Alliierten",
        "„ 7. Marineregiment",
        " 1. Bataillon "
    ],
    "Schlachten/Kriege": [
        "„Persischer Golfkrieg",
        "„Krieg in Afghanistan",
        " Irakkrieg",
        "„ Invasion des Irak",
        "Erste Schlacht von Falludscha",
        " Zweite Schlacht von Falludscha"
    ]
}