{
    "Titel": [
        "David Cassidy"
    ],
    "Geboren": [
        "David Bruce Cassidy, (1950-04-12)April 12, 1950, Manhattan, New York City, USA"
    ],
    "Gestorben": [
        "November 21, 2017(2017-11-21) (im Alter von 67 Jahren), Fort Lauderdale, Florida"
    ],
    "Beruf": [
        "Akteur",
        "Singer",
        "Songwriter",
        "Musiker"
    ],
    "Jahre aktiv": [
        "1969-2017"
    ],
    "Heimatstadt": [
        "West Orange, New Jersey, USA."
    ],
    "Ehefrau(en)": [
        "Kay Lenz, ( m. 1977; div. 1983)",
        "Meryl Tanz, ( m. 1984; div. 1985)",
        "Sue Shifrin, ( m. 1991; div. 2016)"
    ],
    "Kinder": [
        "2, einschließlich Katie Cassidy"
    ],
    "Eltern": [
        "Jack Cassidy",
        "Evelyn Ward"
    ],
    "Familie": [
        "Shaun Cassidy (Halbbruder)",
        "Patrick Cassidy (Halbbruder)",
        "Ryan Cassidy (Halbbruder)"
    ],
    "Genres": [
        "Pop Rock"
    ],
    "Instrumente": [
        "Vocals",
        "Gitarre"
    ],
    "Etiketten": [
        "Bell",
        "Arista",
        "Enigma",
        "Scotti Bros."
    ],
    "Bezeichnungen": [
        "RCA",
        "Slamajama"
    ],
    "Assoziierte Handlungen": [
        "Die Partridge-Familie"
    ],
    "Webseite": [
        "davidcassidy.com"
    ]
}