{
    "Titel": [
        "Cass Ole"
    ],
    "Zucht": [
        "Arabisch"
    ],
    "Herr": [
        "Al-Marah Cassanova [1]"
    ],
    "Grandsire": [
        "Rapture"
    ],
    "Staudamm": [
        "La Bahia"
    ],
    "Großmütterlicherseits": [
        "Hanrah"
    ],
    "Sex": [
        "Stallion"
    ],
    "Fohlen": [
        "6. März 1969"
    ],
    "Land": [
        "Vereinigte Staaten"
    ],
    "Farbe": [
        "Schwarz"
    ],
    "Züchter": [
        "Donoghue Arabians"
    ],
    "Besitzer": [
        "San Antonio Arabians"
    ],
    "Zuletzt aktualisiert": [
        "13. Januar 2008"
    ]
}