{
    "Titel": [
        "Eugen Baumann"
    ],
    "Geboren": [
        "( 1846-12-12 ) 12. Dezember 1846 Cannstatt, Baden-Württemberg, Deutschland"
    ],
    "Gestorben": [
        "3. November 1896 (1896-11-03) (49 Jahre) Freiburg, Baden-Württemberg, Deutschland"
    ],
    "Wohnsitz": [
        "Deutschland"
    ],
    "Nationalität": [
        "Deutsch"
    ],
    "Alma mater": [
        "Universität Tübingen"
    ],
    "bekannt für": [
        "Schotten-Baumann-Reaktion"
    ],
    "Felder": [
        "organische Chemie",
        "physiologische Chemie"
    ],
    "Einrichtungen": [
        "Universität Tubingen"
    ],
    "Institutionen": [
        "Universität Straßburg",
        "Universität Berlin",
        "Universität Freiburg"
    ],
    "Doktorand": [
        "Hermann von Fehling",
        "Felix Hoppe-Seyler"
    ]
}