{
    "शीर्षक": [
        "Justin Theroux"
    ],
    "जन्मा": [
        "Justin Paul Theroux ( 1971-08-10 ) अगस्त 10, 1971 (age 47) वाशिंगटन, डी. सी., अमरीका"
    ],
    "अलम mater": [
        "बेनिंगटन कॉलेज"
    ],
    "व्यवसाय": [
        "कर्ता",
        " comedian ",
        " उत्पादक ",
        "लेखक"
    ],
    "सक्रिय वर्ष": [
        "1995 से वर्तमान"
    ],
    "पति/पत्नी": [
        "जेनिफर एनिस्टोन (2015; सेप्टेम्बर 2018)"
    ],
    "भागीदार": [
        "हेडी बीवन्स (1997-2011)"
    ],
    "नातेदार": [
        "अलेक्जेंडर थ्रोक्स (पैटरनल काक)",
        "पॉल थिरोक्स (पैटरनल काक)",
        "पीटर तेरोक्स (पैटरनल काक)"
    ],
    "रिश्तेदार": [
        "Marcel Theroux (पैटरनल प्रथम cousin)",
        "लुइस तेरोक्स (पैटरनल प्रथम कुटुम्ब)"
    ]
}