{
    "शीर्षक": [
        "चीन"
    ],
    "राजधानी": [
        "北京 39.917; 116.383"
    ],
    "सबसे बड़ा शहर": [
        "शांघाई"
    ],
    "राजभाषाएँ": [
        "मानक चीनी"
    ],
    "मान्यता प्राप्त क्षेत्रीय भाषाएँ": [
        "मोंगोलियन",
        "यूइगर",
        "तिब्बती",
        "जुआंग",
        "विभिन्न अन्य"
    ],
    "Official script": [
        "Simplified Chinese"
    ],
    "सम्मेलन अध्यक्ष": [
        "वांग यांग"
    ],
    "उपनाम": [
        "चाइनिज"
    ],
    "सरकार": [
        "यूनिटरी मार्क्सिस्ट-लेनिनिनिस्ट",
        "एकदलीय समाजवादी गणराज्य"
    ],
    "प्रधानमंत्री": [
        "ली केकियांग"
    ],
    "पार्टी सचिवालय के प्रथम सचिव": [
        "वांग हाउनिंग"
    ],
    "अनुशासन निरीक्षण आयोग के सचिव": [
        "Zhao Leji"
    ],
    "प्रथम उपाध्यक्ष": [
        "हन जंग"
    ],
    "Vice President": [
        "Wang Qishan"
    ],
    "विधानमंडल": [
        "राष्ट्रीय जन कांग्रेस"
    ]
}