{
    "शीर्षक": [
        "Dead Can Dance"
    ],
    "मूल": [
        "मेलबोर्न, ऑस्ट्रेलिया"
    ],
    "विधाएँ": [
        "नियोclassical dark wave",
        "विश्व",
        "आर्ट रॉक",
        "अग्रणी",
        "गोथिक रॉक"
    ],
    "वर्ष सक्रिय": [
        "1981-1998",
        "2005",
        "2011-present"
    ],
    "लेबल": [
        "4AD, वॉरनर ब्रॉस",
        "Rhino/Atlantic",
        "Rykodisc",
        "पीआईएस"
    ],
    "संबद्ध कलाकार": [
        "द स्कैविंगर्स",
        "द मार्शिंग गेल्स",
        "जंक लॉजिक",
        "माइक्रोफ़िल्म",
        "स्वर्गीय शरीर",
        "पीटर बोर्क"
    ],
    "वेबसाइट": [
        "deadcandance.com"
    ]
}