{
    "शीर्षक": [
        "Cloud Atlas"
    ],
    "निर्देश:": [
        "लाना वचॉस्की",
        "आडी वचॉस्की"
    ],
    "Regied by": [
        "Tom Tykwer"
    ],
    "प्रोड्यूसर द्वारा": [
        "स्टेफन अर्ंड",
        "टोम टाइकर"
    ],
    "प्रोड्यूसर": [
        "ग्रांट हिल"
    ],
    "द्वारा उत्पादित": [
        "लाना वचॉस्की",
        "एण्डी वचॉस्की"
    ],
    "स्क्रीनशॉप द्वारा": [
        "लाना वाचowski",
        "टोम टाइकर",
        "Andy Wachowski"
    ],
    "पर आधारित": [
        "क्लाउड एटलस, डेविड मिचेल"
    ],
    "主演": [
        "टोम हैंक्स",
        "हले बेरी",
        "जिम ब्रैडबेंट",
        "जिम स्टर्ज्स",
        "डोना बे",
        "बेन विशाव",
        "James D'Arcy",
        "ज़ु क़ुन",
        "कीथ डेविड",
        "David Gyasi",
        "सुसान सरंडन",
        "हugh grant"
    ],
    "स्टाररंग": [
        "हुगो वेविंग"
    ],
    "संगीत द्वारा": [
        "टोम टाइकर",
        "Johnny Klimek",
        "Reinhold Heil"
    ],
    "चलचित्र": [
        "John Toll",
        "फ्रेंक ग्राइब"
    ],
    "Edited by": [
        "Alexander Berner"
    ],
    "निर्माणकंपनियां": [
        "Cloud Atlas Production"
    ],
    "उत्पादक कंपनियां": [
        "X-Filme Creative Pool",
        "अनार्कोस प्रोडक्शन्स"
    ],
    "वितरितः": [
        "वॉरनर ब्रॉस फिल्म्स (उत्तर अमेरिका और यूनाइटेड किंगडम), एक्स-वर्लेह (जर्मन), फ़ोकस फ़ोक्स (आंतरराष्ट्रीय)"
    ],
    "रिलीज़ तिथि": [
        "8 सितंबर 2012 (2012-09-08) (TIFF)",
        "26 अक्तूबर 2012 (2012-10-26) (North America)",
        "15 नवंबर 2012 (2012-11-15) (जर्मन)"
    ],
    "रनिंग समय": [
        "171 मिनट"
    ],
    "देश": [
        "जर्मिया",
        "यूनाइटेड स्टेट्स"
    ],
    "भाषा": [
        "अंग्रेज़ी"
    ],
    "बजट": [
        "$128.5 (नेट) $146.7 (gross) मिलियन"
    ],
    "बॉक्स ऑफिस": [
        "130.5 मिलियन डॉलर"
    ]
}