{
    "शीर्षक": [
        "35/36 मेट्रो लाइनें"
    ],
    "तंत्र": [
        "एग्डर कोल्लेक्टिव ट्रांसपोर्ट"
    ],
    "ऑपरेटर": [
        "नेटबस"
    ],
    "गैराज": [
        "Mjåvann, Sørlandsparken"
    ],
    "वाहन": [
        "Mercedes-Benz Citaro"
    ],
    "Locale": [
        "Kvadraturen - UiA - Rona - Tveit"
    ],
    "प्रारंभ": [
        "35: क्वाड्राटूरें, 36: क्वाड्राटूरें, 36: वी"
    ],
    "Via": [
        "UiA, Rona"
    ],
    "अंत": [
        "35: Kjevik - Brattvollsheia, 36: Tveit - Grødum, 36: Grødum"
    ],
    "काम करती हैं": [
        "17 घंटे (35), 05:15 से 00:15, 2 घंटे (36), 15:00 से 16:00, 10 घंटे (36), 07:40 से 22:40"
    ],
    "अंतरण": [
        "हाँ"
    ],
    "समय सारणी": [
        "35/36"
    ]
}