{
    "शीर्षक": [
        "काटी पेरी"
    ],
    "जन्मा": [
        "25 अक्तूबर, 1984 (34 वर्ष की आयु) Santa Barbara, California, U.S."
    ],
    "जन्म नाम": [
        "केथरिन एलिजाबेथ हडसन"
    ],
    "अन्य नाम": [
        "काटी हडसन",
        "Katheryn Perry"
    ],
    "व्यवसाय": [
        "सिंगर",
        "संगीतकार",
        "'' कलाकार ''",
        "व्यापारिक महिला",
        "हितप्रिय",
        "टेलीविजन न्यायाधीश"
    ],
    "शुद्ध मूल्य": [
        "$125 मिलियन (2016 अनुमान)"
    ],
    "पति/पत्नी": [
        "रसेल ब्रांड (एम. 2010; डि. 2012)"
    ],
    "रिश्तेदार": [
        "फ्रेंक पेरी (अंका)"
    ],
    "विधाएँ": [
        "पॉप",
        "रॉक"
    ],
    "वाद्य": [
        "Vocals",
        "गिटार"
    ],
    "वर्ष सक्रिय": [
        "2001-present"
    ],
    "लेबल": [
        "Red Hill",
        "Java",
        "कोलम्बिया",
        "कैपिटोल"
    ],
    "संबद्ध कलाकार": [
        "द मैट्रिक्स"
    ],
    "वेबसाइट": [
        "katyperry.com"
    ]
}