{
    "titre": [
        "Jacques Cousteau"
    ],
    "N\u00e9": [
        "11 juin 1910 Saint-Andre-de-Cubzac, France"
    ],
    "Nom de naissance": [
        "Jacques-Yves Cousteau"
    ],
    "D\u00e9c\u00e9d\u00e9": [
        "25 juin 1997 (87 ans) Paris, France"
    ],
    "Nationalit\u00e9": [
        "Fran\u00e7ais"
    ],
    "Profession": [
        "Oc\u00e9anographe"
    ],
    "Conjoint(s)": [
        "Simone Melchior Cousteau (1937-1990, sa mort)",
        "Francine Triplet Cousteau (1991-1997)"
    ],
    "Enfants": [
        "Jean-Michel",
        "Philippe Cousteau",
        "Diane",
        "Pierre-Yves"
    ]
}