{
    "titre": [
        "Dean Kamen"
    ],
    "N\u00e9": [
        "(1951-04-05) 5 avril 1951 (67 ans), Long Island, New York, \u00c9tats-Unis"
    ],
    "R\u00e9sidence": [
        "Bedford, New Hampshire, \u00c9tats-Unis."
    ],
    "Nationalit\u00e9": [
        "Am\u00e9ricain"
    ],
    "Connu pour": [
        "Invention du fauteuil roulant iBot, le Segway et fondateur de FIRST, North Dumpling Island"
    ],
    "Prix": [
        "M\u00e9daille Hoover (1995)",
        "Heinz en technologie",
        "L'\u00e9conomie et l'emploi (1999)",
        "M\u00e9daille nationale de la technologie et de l'innovation (2000)",
        "Prix Lemelson-MIT (2002)",
        "M\u00e9daille ASME (2007)",
        "Prix Lindbergh (2011)",
        "Prix humanitaire mondial (2013)"
    ]
}