{
    "titre": [
        "Johnny Hallyday"
    ],
    "N\u00e9": [
        "15 juin 1943 Paris, France"
    ],
    "Nom de naissance": [
        "Jean-Philippe Leo Smet"
    ],
    "D\u00e9c\u00e9d\u00e9": [
        "5 d\u00e9cembre 2017 (2017-12-05) (74 ans) Marnes-la-Coquette, France"
    ],
    "Lieu de repos": [
        "Saint Barthelemy"
    ],
    "Profession": [
        "auteur-compositeur-compositeur-compositeur-compositeur-compositeur-compositeur-compositeur-compositeur",
        "musicien",
        "acteur"
    ],
    "Conjoint(s)": [
        "Sylvie Vartan ( m. 1965; div. 1980)",
        "Babeth Etienne ( m. 1981; div. 1982)",
        "Adeline Blondieau ( m. 1990; div. 1992) ( m. 1994; div. 1995)",
        "Laeticia Hallyday (m. 1996)"
    ],
    "Partenaire(s)": [
        "Nathalie Baye (1982-1986)"
    ],
    "Enfants": [
        "4 (y compris David et Laura)"
    ],
    "Genres": [
        "Rock and roll",
        "pop"
    ],
    "Instruments": [
        "Vocals",
        "piano",
        "guitare"
    ],
    "Ann\u00e9es d'activit\u00e9": [
        "1959-2017"
    ],
    "Etiquettes": [
        "Vogue",
        "Philips",
        "Warner",
        "Universel"
    ],
    "Actes associ\u00e9s": [
        "Mick Jones",
        "Tommy Brown",
        "Dalida",
        "Sylvie Vartan",
        "Bono",
        "L'exp\u00e9rience Jimi Hendrix",
        "Connie Francis"
    ],
    "Site web": [
        "johnnyhallyday.com"
    ]
}