{
    "title": [
        "Charles Snead Houston"
    ],
    "Born": [
        "24 \u0430\u0432\u0433\u0443\u0441\u0442\u0430 1913 ( 1913-08-24 ) New York City, New York"
    ],
    "\u0423\u043c\u0435\u0440": [
        "27 \u0441\u0435\u043d\u0442\u044f\u0431\u0440\u044f 2009 (2009-09-27) (\u0432\u043e\u0437\u0440\u0430\u0441\u0442 96) Burlington, Vermont"
    ],
    "Education": [
        "Harvard College",
        "Columbia University College of Physicians and Surgeons"
    ],
    "\u041f\u0440\u043e\u0444\u0435\u0441\u0441\u0438\u044f": [
        "Physician",
        "\u041c\u043euntaineer",
        "\u041d\u0430\u0443\u0447\u043d\u044b\u0439",
        "Administrator Peace Corps"
    ],
    "Spouse(s)": [
        "Dorcas Laidley Tiemeyer (\u043c. 1941)"
    ],
    "\u0414\u0435\u0442\u0438": [
        "1 \u0434\u043e\u0447\u044c \u041f\u0435\u043d\u043d\u0438, \u0438 \u0434\u0432\u0430 \u0441\u044b\u043d\u0430 \u0414\u0430\u0432\u0438\u0434\u0430 \u0438 \u0420\u043e\u0431\u0438\u043d\u0430."
    ],
    "Parent(s)": [
        "Oscar Rempel Houston",
        "Nelly Snead MacDonald"
    ]
}