{
    "titel": [
        "Lusaka Mwalusaka"
    ],
    "Ko\u00f6rdinate": [
        "15\u00b025\u2032S 28\u00b017\u2032E / 15.417\u00b0S 28.283\u00b0E"
    ],
    "Provinsie": [
        "Lusaka Provinsie"
    ],
    "District": [
        "Lusaka District"
    ],
    "Land": [
        "Zambia"
    ],
    "Geskep": [
        "1905"
    ],
    "Stad status": [
        "25 augustus 1960"
    ],
    "burgemeester van Lusaka": [
        "Miles Sampa"
    ],
    "Stad": [
        "Bevolking: 1. 747. 152",
        "Area: 418 km2 (161 sq mi)"
    ],
    "Lift": [
        "1. 299 m (4. 190 ft)"
    ],
    "Metro": [
        "2. 238.569"
    ],
    "Tydzone": [
        "UTC+2 (CAT)"
    ],
    "Area kode( s)": [
        "0211"
    ],
    "Klimaat": [
        "Cwa"
    ],
    "Website": [
        "http://www.lcc.gov.zm"
    ]
}