{
    "titel": [
        "WIMA"
    ],
    "Gesloon": [
        "1950"
    ],
    "Ligging": [
        "Vereenigde State"
    ],
    "Fondeerder": [
        "Louise Scherbyn"
    ],
    "Leider": [
        "Asa \u00d6hqvist (2017)"
    ],
    "Leider titel": [
        "President"
    ],
    "Sleutelspeakers": [
        "Theresa Wallach, eerste International Vice-President"
    ],
    "Tipe": [
        "Association"
    ],
    "Streek": [
        "Wereldwijd"
    ],
    "Betekenis": [
        "Damen motorcyclist"
    ],
    "Aktiwiteite": [
        "Pink RIbbon Rides"
    ],
    "Webruimte": [
        "www.wimaworld.com"
    ],
    "Kortpad": [
        "WIMA"
    ]
}