{
    "titel": [
        "Jumanji"
    ],
    "Rerig deur": [
        "Joe Johnston"
    ],
    "Vertoon deur": [
        "Scott Kroopf",
        "William Teitler"
    ],
    "Screenplay deur": [
        "Greg Taylor"
    ],
    "Screenplay by": [
        "Jonathan Hensleigh",
        "Jim Strain"
    ],
    "Story by": [
        "Greg Taylor",
        "Jim Strain",
        "Chris Van Allsburg"
    ],
    "Gebaseer op": [
        "Jumanji deur Chris Van Allsburg"
    ],
    "Rerig": [
        "Robin Williams",
        "Kirsten Dunst",
        "David Alan Grier",
        "Bonnie Hunt",
        "Jonathan Hyde",
        "Bebe Neuwirth"
    ],
    "Musiek deur": [
        "James Horner"
    ],
    "Cinematografie": [
        "Thomas E. Ackerman"
    ],
    "Redigeer deur": [
        "Robert Dalva"
    ],
    "Verspreiding deur": [
        "TriStar Pictures"
    ],
    "Verwyder date": [
        "December 15, 1995 ( 1995-12-15 )"
    ],
    "Wat loop tyd": [
        "104 minute"
    ],
    "Land": [
        "Vereenigde State"
    ],
    "Taal": [
        " Engels"
    ],
    "Budget": [
        "$65 miljoen"
    ],
    "Boksoffice": [
        "$262.8 miljoen"
    ],
    "Produksie span": [
        "Interscope Communications",
        "Teitler Film"
    ]
}