{
    "titel": [
        "Hardrock Hundred Mile Endurance Run"
    ],
    "Datum": [
        "July"
    ],
    "Ligging": [
        "Silverton, Colorado"
    ],
    "Gebeurtenis tipe": [
        "Ultramarathon trail run"
    ],
    "Afstand": [
        "100.5- myle (161.7 km)"
    ],
    "Geskep": [
        "1992"
    ],
    "Natuurlik rekord": [
        "Kilian Jornet 23:28:10 (2015, anti- kloksgewys), Kilian Jornet 22:41:33 (2014, kloksgewys)"
    ],
    "Offisionele site": [
        "http://www.hardrock100.com/"
    ]
}