{
    "titel": [
        "Ice hockey"
    ],
    "Hoogste Regering Organism": [
        "International Ice Hockey Federation"
    ],
    "Kontak": [
        "Volgrote kontak"
    ],
    "Drukkers": [
        "3 Vorentoe",
        "2 Beskermsman",
        "1 Goaltender"
    ],
    "Tipe": [
        "Team sport",
        "stick sport",
        "puck sport",
        "jaar sport"
    ],
    "Gereedskap": [
        "Hockey pucks",
        "sticks",
        "skate",
        "shin pads",
        "skaalpak",
        "handschoenen",
        "helmets (met houer of kooi, afhangend op leeftijd van speler en ligue)",
        "elbow pads",
        "jock of jill",
        "socks",
        "shorts",
        "Neck Guard (afhanklik van ligue)",
        "mouthguard (afhanklik van ligue)"
    ],
    "Venue": [
        "hockey rink of arena, en is soms gespeel op 'n bevroren meer of staw vir vermaak"
    ]
}