{
    "titel": [
        "John Augustus Larson"
    ],
    "Geboren": [
        "( 1892-12-11 ) December 11, 1892 Shelburne, Nova Scotia, Canada"
    ],
    "Gestorven": [
        "Oktober 1, 1965 (1965-10-01) (grootte 72) Berkeley"
    ],
    "Residensie": [
        "Berkeley, California"
    ],
    "Nationaliteit": [
        "Amerikaanse"
    ],
    "Burgerskap": [
        "U. S."
    ],
    "Onderwijs": [
        "Boston Universiteit (M.Sc., 1915)",
        "Universiteit van Californi\u00eb, Berkeley (Ph.D., 1920)"
    ],
    "Alma mater": [
        "Universiteit van Californi\u00eb, Berkeley"
    ],
    "bekend vir": [
        "Criminology",
        "Polygrafie"
    ],
    "Velde": [
        "Medi\u00ebnse Criminologie"
    ]
}