{
    "titel": [
        "Florence en die Masjien"
    ],
    "Oorspronklike": [
        "London, England"
    ],
    "Genre": [
        "Indie rock",
        "indie pop",
        "baroque pop",
        "kunstrock",
        "kunst pop",
        "neo soul",
        "folk"
    ],
    "Genres": [
        "chamber pop"
    ],
    "Jare aktief": [
        "2007 - huidige"
    ],
    "Labels": [
        "Moshi Moshi",
        "Iamsound",
        "Island",
        "Republic",
        "Universal Republic",
        "Virgin EMI"
    ],
    "Geassosieerde aktiwiteite": [
        "Dizzee Rascal",
        "The Big Pink",
        "Die Horrors",
        "Dev Hynes"
    ],
    "Associeerde aktiwiteite": [
        "Kid Harpoon"
    ],
    "Webruimte": [
        "florenceandthemachine.net"
    ]
}