{
    "titre": [
        "Traitements"
    ],
    "Ann\u00e9es d'activit\u00e9": [
        "au moins 5 000"
    ],
    "Genre(s)": [
        "Jeu de soci\u00e9t\u00e9, Abstraction jeu de strat\u00e9gie, Mind sport"
    ],
    "Joueurs": [
        "2"
    ],
    "Temps de configuration": [
        "&lt;1 minute"
    ],
    "Temps de jeu": [
        "30 minutes - 2 heures"
    ],
    "hasard al\u00e9atoire": [
        "Aucun"
    ],
    "Comp\u00e9tence(s) requise(s)": [
        "Strat\u00e9gie, tactique"
    ],
    "Synonyme(s)": [
        "V\u00e9rificateurs, Ch\u00e8ques"
    ]
}