{
    "titre": [
        "Phnom Penh "
    ],
    "Fond\u00e9e": [
        "1372"
    ],
    "Pseudo(s)": [
        "Perle d'Asie (avant les ann\u00e9es 1960) La ville charmante"
    ],
    "Situation financi\u00e8re": [
        "1434-1497"
    ],
    "Coordonn\u00e9es": [
        "11\u00b034\u203210\u2032\u2032N 104\u00b055\u203216\u2032\u2032E / 11.56944\u00b0N 104.92111\u00b0E"
    ],
    "Statut r\u00e9gularis\u00e9": [
        "1865"
    ],
    "Nomm\u00e9 pour": [
        "Wat Phnom"
    ],
    "Subdivisions": [
        "14 districts (khans)"
    ],
    "Type": [
        "Conseil municipal"
    ],
    "Gouverneur": [
        "Khuong Sreng (CPP)"
    ],
    "Assembl\u00e9e nationale": [
        "12 / 125"
    ],
    "Total": [
        "679 km 2 (262 mi2)"
    ],
    "Classement r\u00e9gional": [
        "24e"
    ],
    "El\u00e9vation": [
        "11.89 m (39.01 ft)"
    ],
    "Classement de la population (2019)": [
        "1er"
    ],
    "Densit\u00e9 (2019)": [
        "3,136/km 2 (8,120/sq mi)"
    ],
    "Classement de la densit\u00e9 (2019)": [
        "1er"
    ],
    "Demonym(s)": [
        "Phnom Penher, (fran\u00e7ais: Phnom Penhois(e) )"
    ],
    "Fuseau horaire": [
        "UTC+07:00 (TIC)"
    ],
    "Code(s) r\u00e9gional(s)": [
        "+855 (023)"
    ],
    "IDH (2017)": [
        "0,712, haut \u00b7 1\u00e8re"
    ],
    "Site Web": [
        "www.phnompenh.gov.kh/"
    ]
}