{
    "titre": [
        "Me m\u00e9prisable 3"
    ],
    "R\u00e9alis\u00e9 par": [
        "Pierre Coffin",
        "Kyle Balda"
    ],
    "Produit par": [
        "Chris Meledandri",
        "Janet Healy"
    ],
    "\u00c9crit par": [
        "Cinco Paul",
        "Ken Daurio"
    ],
    "En vedette": [
        "Steve Carell",
        "Trey Parker",
        "Miranda Cosgrove",
        "Steve Coogan",
        "Jenny Slate",
        "Dana Gaier",
        "Julie Andrews"
    ],
    "Starring": [
        "Kristen Wiig"
    ],
    "Musique de": [
        "Heitor Pereira"
    ],
    "Edit\u00e9 par": [
        "Claire Dodgson"
    ],
    "Soci\u00e9t\u00e9 de production": [
        "Images universelles",
        "Illumination"
    ],
    "Distribu\u00e9 par": [
        "Photos universelles"
    ],
    "Date de sortie": [
        "14 juin 2017 ( 2017-06-14 ) (Annecy)",
        "30 juin 2017 ( 2017-06-30 ) (\u00c9tats-Unis)"
    ],
    "Dur\u00e9e": [
        "90 minutes"
    ],
    "Pays": [
        "\u00c9tats-Unis"
    ],
    "Langue": [
        "Anglais"
    ],
    "Budget": [
        "80 millions de dollars"
    ],
    "Box-office": [
        "1 034 milliards de dollars"
    ]
}