{
    "T\u00edtulo": [
        "\u201cJoy\u201d"
    ],
    "dirigida por": [
        "\u201cDavid O. Russell\u201d"
    ],
    "Producida por": [
        "\u201cJohn Davis\u201d",
        "\u201cMegan Ellison\u201d",
        "\u201cJonathan Gordon\u201d",
        "\u201cKen Mok\u201d",
        "\u201cDavid O. Russell\u201d"
    ],
    "Gui\u00f3n": [
        "\u201cDavid O. Russell\u201d"
    ],
    "Historia de": [
        "\u201cAnnie Mumolo\u201d",
        "\u201cDavid O. Russell\u201d"
    ],
    "Starring": [
        "\u201cJennifer Lawrence\u201d",
        "\u201cRobert De Niro\u201d",
        "\u201cEdgar Ramirez\u201d",
        "\u201cDiane Ladd\u201d",
        "\u201cVirginia Madsen\u201d",
        "\u201cBradley Cooper\u201d"
    ],
    "protagonizada por": [
        "\u201cIsabella Rossellini\u201d"
    ],
    "M\u00fasica de": [
        "West Dylan Thordson",
        "\u201cDavid Campbell\u201d"
    ],
    "Cinematograf\u00eda": [
        "\u201cLinus Sandgren\u201d"
    ],
    "Editado por": [
        "Alan Baumgarten",
        "Jay Cassidy",
        "\u201cTom Cross\u201d",
        "Christopher Tellefsen"
    ],
    "Distribuida por": [
        "\u201c20th Century Fox\u201d"
    ],
    "Fecha de lanzamiento": [
        "13 de diciembre de 2015 ( 2015-12-13 ) (Nueva York) 25 de diciembre de 2015 ( 2015-12-25 ) (Estados Unidos)"
    ],
    "Tiempo de ejecuci\u00f3n": [
        "124 minutos"
    ],
    "Pa\u00eds": [
        "\u00abEstados Unidos de Am\u00e9rica\u00bb"
    ],
    "Lenguaje": [
        "\u201cIngl\u00e9s\u201d"
    ],
    "Presupuesto": [
        "$60 millones"
    ],
    "Box Office": [
        "$101.1 millones"
    ],
    "Producci\u00f3n": [
        "Fox 2000 Pictures",
        "Davis Entertainment Company",
        "Annapurna Pictures",
        "TSG Entertainment"
    ]
}