{
    "t\u00edtulo": [
        "\u00abBrooklyn Bridge\u00bb"
    ],
    "Transporta": [
        "6 carriles de carretera (s\u00f3lo coches), Tren elevado (hasta 1944), Carreras (hasta 1950), Peatones y bicicletas"
    ],
    "Crucero": [
        "\u201cR\u00edo Oriental\u201d"
    ],
    "Locale": [
        "Nueva York (Civic Center, Manhattan - Dumbo/Brooklyn Heights, Brooklyn)"
    ],
    "Mantenido por": [
        "Departamento de Transporte de la Ciudad de Nueva York"
    ],
    "N\u00famero de identificaci\u00f3n": [
        "22400119"
    ],
    "Dise\u00f1o": [
        "Suspension/Cable-stay Hybrid"
    ],
    "Longitud total": [
        "6.016 pies (1,833.7 m)"
    ],
    "Ancho": [
        "85 pies (25.9 m)"
    ],
    "Altitud": [
        "272 pies (82.9 m) (torres)"
    ],
    "M\u00e1s largo": [
        "1,595.5 pies (486.3 m)"
    ],
    "Claridad por debajo de": [
        "133 pies (40,5 m) por encima del agua media alta"
    ],
    "Dise\u00f1ador": [
        "\u201cJohn Augustus Roebling\u201d"
    ],
    "Abierto": [
        "24 de mayo de 1883; hace 136 a\u00f1os (1883-05-24)"
    ],
    "Tr\u00e1fico diario": [
        "105,679 (2016)"
    ],
    "Toll": [
        "Libre de ambos modos"
    ]
}