{
    "t\u00edtulo": [
        "\u201cJada Pinkett Smith\u201d"
    ],
    "Nacido": [
        "( 1971-09-18 ) 18 de septiembre de 1971 (edad 47) Baltimore, Maryland, Estados Unidos"
    ],
    "Nombre de nacimiento": [
        "Jada Koren Pinkett"
    ],
    "Residencia": [
        "Malibu, California, Estados Unidos"
    ],
    "Otros nombres": [
        "Jada Koren (con la sabidur\u00eda malvada)"
    ],
    "Ocupaci\u00f3n": [
        "\u201cActor\u201d",
        "Cantante y compositor",
        "\u201cMujer de negocios\u201d"
    ],
    "A\u00f1os activos": [
        "1990 presente"
    ],
    "Esposo (s)": [
        "Will Smith (m. 1997)"
    ],
    "Ni\u00f1os": [
        "\u201cJaden Smith\u201d",
        "\u201cWillow Smith\u201d"
    ],
    "P\u00e1gina web": [
        "jadapinkettsmith.com"
    ]
}