{
    "T\u00edtulo": [
        "Sacred Mother Tongue"
    ],
    "Tambi\u00e9n conocido como": [
        "SMT"
    ],
    "Origen": [
        "Northampton, Inglaterra, Reino Unido"
    ],
    "G\u00e9neros": [
        "\u201cMetalcore\u201d",
        "metal pesado",
        "melodic death metal (early)"
    ],
    "A\u00f1os activos": [
        "2004-2013"
    ],
    "Etiquetas": [
        "Transcend Music, EMI Label Services"
    ],
    "Sitio web": [
        "www.sacredmothertongue.com"
    ],
    "Miembros": [
        "\u201cDarrin South, Andy James, Craig Daws, Lee Newell\u201d"
    ]
}