{
    "t\u00edtulo": [
        "\u201cGrupo Danieli\u201d"
    ],
    "Tipo": [
        "Societ\u00e0 per azioni"
    ],
    "Traducido como": [
        "BIT: DAN"
    ],
    "Industria": [
        "Metal, fabricaci\u00f3n, acero"
    ],
    "Fundada": [
        "1914"
    ],
    "Fundadores": [
        "Mario Danieli, Timo Danieli"
    ],
    "Sede": [
        "Buttrio, Italia"
    ],
    "Personas clave": [
        "Gianpietro Benedetti, Presidente, Giacomo Mareschi Danieli, CEO, Alessandro Trivillin, CEO"
    ],
    "Productos": [
        "Inxenier\u00eda, equipos, plantas"
    ],
    "Ingresos": [
        "2.706 millones de euros (2018)"
    ],
    "Ingresos operativos": [
        "\u20ac0.58 mil millones (2018)"
    ],
    "Ingresos netos": [
        "1.853 millones de euros (2018)"
    ],
    "N\u00famero de empleados": [
        "9,358 (2018)"
    ],
    "Sitio web": [
        "danieli.com"
    ]
}