{
    "T\u00edtulo": [
        "Rep\u00fablica Checa"
    ],
    "Religi\u00f3n (2011)": [
        "44.7% no declarado",
        "34.5% no religioso",
        "10,5% Cat\u00f3lico",
        "2,1% otros cristianos",
        "0.7% otras religiones"
    ],
    "Idioma oficial": [
        "Corea del Sur"
    ],
    "Demonym(s)": [
        "China"
    ],
    "Gobierno": [
        "Rep\u00fablica Unitaria Parlamentaria Constitucional"
    ],
    "Presidente": [
        "\u201cMilos Zeman\u201d"
    ],
    "Primer Ministro": [
        "Andrej Babis"
    ],
    "Legislatura": [
        "\u00abParlamento\u00bb"
    ],
    "C\u00e1mara Alta": [
        "\u00abSenado\u00bb"
    ],
    "C\u00e1mara baja": [
        "C\u00e1mara de Diputados"
    ]
}