{
    "T\u00edtulo": [
        "\u00abIslamabad\u00bb"
    ],
    "Capital ciudad": [
        "906.5 km2 (350.0 sq mi)"
    ],
    "Tierra": [
        "897.7 km2 (346.6 kil\u00f3metros cuadrados)"
    ],
    "Agua": [
        "8.8 km2 (3.4 millas cuadradas) 0.97%"
    ],
    "Urbano": [
        "220.15 km2 (85.00 kil\u00f3metros cuadrados)"
    ],
    "Rural": [
        "466.20 km2 (180.00 km2)"
    ],
    "Parques": [
        "220.15 km2 (85.00 kil\u00f3metros cuadrados)"
    ],
    "Altitud m\u00e1xima": [
        "620 m (2000 pies)"
    ],
    "Altitud m\u00e1s baja": [
        "490 m (1,610 pies)"
    ]
}