{
    "T\u00edtulo": [
        "\u201cHulk\u201d"
    ],
    "dirigida por": [
        "\u201cAng Lee\u201d"
    ],
    "Producida por": [
        "\u201cAvi Arad\u201d",
        "Larry J. Franco",
        "Gale Anne Hurd",
        "\u201cJames Schamus\u201d"
    ],
    "Gui\u00f3n por": [
        "\u201cJames Schamus\u201d",
        "Michael France",
        "\u201cJohn Turman\u201d"
    ],
    "Historia de": [
        "\u201cJames Schamus\u201d"
    ],
    "Basado en": [
        "El Hulk de Stan Lee Jack Kirby"
    ],
    "Starring": [
        "\u201cEric Bana\u201d",
        "\u201cJennifer Connelly\u201d",
        "\u201cSam Elliott\u201d",
        "\u201cJosh Lucas\u201d",
        "\u201cNick Nolte\u201d"
    ],
    "M\u00fasica de": [
        "\u201cAlan Silvestri\u201d"
    ],
    "Cinematograf\u00eda": [
        "\u201cDon Burgess\u201d"
    ],
    "Editado por": [
        "Tim Squyres"
    ],
    "Compa\u00f1\u00eda de producci\u00f3n": [
        "Marvel Enterprises"
    ],
    "Producci\u00f3n": [
        "Valhalla Motion Pictures",
        "\u201cGood Machine\u201d"
    ],
    "Distribuida por": [
        "Universal Pictures"
    ],
    "Fecha de lanzamiento": [
        "20 de junio de 2003"
    ],
    "Tiempo de ejecuci\u00f3n": [
        "138 minutos"
    ],
    "Pa\u00eds": [
        "\u00abEstados Unidos de Am\u00e9rica\u00bb"
    ],
    "Lenguaje": [
        "\u201cIngl\u00e9s\u201d"
    ],
    "Presupuesto": [
        "$137 millones"
    ],
    "Box Office": [
        "$245.4 millones"
    ]
}